st_card_alert_2/__init__.py
st_card_alert_2/main.py
st_card_alert_2/frontend/build/asset-manifest.json
st_card_alert_2/frontend/build/bootstrap.min.css
st_card_alert_2/frontend/build/index.html
st_card_alert_2/frontend/build/precache-manifest.97c96c1c7639b135f5d990a6dcf2ae4a.js
st_card_alert_2/frontend/build/service-worker.js
st_card_alert_2/frontend/build/static/js/2.0dc3e5ca.chunk.js
st_card_alert_2/frontend/build/static/js/2.0dc3e5ca.chunk.js.LICENSE.txt
st_card_alert_2/frontend/build/static/js/2.0dc3e5ca.chunk.js.map
st_card_alert_2/frontend/build/static/js/main.91ba057a.chunk.js
st_card_alert_2/frontend/build/static/js/main.91ba057a.chunk.js.map
st_card_alert_2/frontend/build/static/js/runtime-main.11ec9aca.js
st_card_alert_2/frontend/build/static/js/runtime-main.11ec9aca.js.map
st_card_alert_2-0.0.1.dist-info/LICENSE
st_card_alert_2-0.0.1.dist-info/METADATA
st_card_alert_2-0.0.1.dist-info/WHEEL
st_card_alert_2-0.0.1.dist-info/top_level.txt
st_card_alert_2-0.0.1.dist-info/RECORD
